[
  {
    "id": "9mr051gm",
    "game": "Terminator 2:Judgment Day",
    "player": "Gusnation",
    "player_location": null,
    "time": 813,
    "category": "",
    "region": "USA / NTSC",
    "platform": "Nintendo Entertainment System",
    "emulated": false
  },
  {
    "id": "m3dxg36z",
    "game": "Terminator 2:Judgment Day",
    "player": "DTysonator",
    "player_location": "ca",
    "time": 1055,
    "category": "Beat The Game",
    "region": "USA / NTSC",
    "platform": "Nintendo Entertainment System",
    "emulated": false
  },
  {
    "id": "y8qw6ony",
    "game": "Terminator 2:Judgment Day",
    "player": "vmikea",
    "player_location": "ru",
    "time": 825,
    "category": "Beat The Game",
    "region": "USA / NTSC",
    "platform": "Nintendo Entertainment System",
    "emulated": true
  },
  {
    "id": "ywp4xenz",
    "game": "Terminator 2:Judgment Day",
    "player": "Mr.Filz",
    "player_location": "de",
    "time": 837,
    "category": "Beat The Game",
    "region": "USA / NTSC",
    "platform": "Nintendo Entertainment System",
    "emulated": false
  },
  {
    "id": "zg7pwgjz",
    "game": "Terminator 2:Judgment Day",
    "player": "Mad_Max",
    "player_location": "fr",
    "time": 711,
    "category": "Beat The Game",
    "region": "USA / NTSC",
    "platform": "Nintendo Entertainment System",
    "emulated": true
  },
  {
    "id": "zq4q68xm",
    "game": "Terminator 2:Judgment Day",
    "player": "timmyshotgun",
    "player_location": "mq",
    "time": 691,
    "category": "Beat The Game",
    "region": "JPN / NTSC",
    "platform": "Nintendo Entertainment System",
    "emulated": false
  },
  {
    "id": "mk34v11z",
    "game": "Terminator 2:Judgment Day",
    "player": "emagen303",
    "player_location": "us",
    "time": 864,
    "category": "Beat The Game",
    "region": "USA / NTSC",
    "platform": "Nintendo Entertainment System",
    "emulated": false
  },
  {
    "id": "yokj611z",
    "game": "Terminator 2:Judgment Day",
    "player": "YuaRyuc",
    "player_location": "jp",
    "time": 852,
    "category": "Beat The Game",
    "region": null,
    "platform": "Nintendo Entertainment System",
    "emulated": false
  },
  {
    "id": "m75q9rwz",
    "game": "Terminator 2:Judgment Day",
    "player": "Jrmhd91",
    "player_location": "us",
    "time": 982,
    "category": "Beat The Game",
    "region": null,
    "platform": "Nintendo Entertainment System",
    "emulated": false
  },
  {
    "id": "z537l0jy",
    "game": "Terminator 2:Judgment Day",
    "player": "Tishero",
    "player_location": "us",
    "time": 846,
    "category": "Beat The Game",
    "region": null,
    "platform": "Nintendo Entertainment System",
    "emulated": false
  },
  {
    "id": "y4e6j3km",
    "game": "Terminator 2:Judgment Day",
    "player": "Pikachu",
    "player_location": "ua",
    "time": 682,
    "category": "Beat The Game",
    "region": "JPN / NTSC",
    "platform": "Nintendo Entertainment System",
    "emulated": false
  },
  {
    "id": "m37w2oqz",
    "game": "Terminator 2:Judgment Day",
    "player": "Sensei_Vitek",
    "player_location": "ru",
    "time": 920,
    "category": "Beat The Game",
    "region": "USA / NTSC",
    "platform": "Nintendo Entertainment System",
    "emulated": true
  },
  {
    "id": "y9l18gky",
    "game": "Terminator 2:Judgment Day",
    "player": "stereodoGGG",
    "player_location": "ca",
    "time": 731,
    "category": "Beat The Game",
    "region": "JPN / NTSC",
    "platform": "Nintendo Entertainment System",
    "emulated": true
  },
  {
    "id": "ylexew3z",
    "game": "Terminator 2:Judgment Day",
    "player": "betaxcomplainer",
    "player_location": "us",
    "time": 798,
    "category": "Beat The Game",
    "region": "USA / NTSC",
    "platform": "Nintendo Entertainment System",
    "emulated": false
  },
  {
    "id": "mrrx1j2m",
    "game": "Terminator 2:Judgment Day",
    "player": "JacksonTV",
    "player_location": "ru",
    "time": 860,
    "category": "Beat The Game",
    "region": "JPN / NTSC",
    "platform": "Nintendo Entertainment System",
    "emulated": true
  }
]