[
  {
    "id": "ylrp6rny",
    "game": "Where\u2019s My Head?",
    "player": "Jacob1",
    "player_location": "ca",
    "time": 0.4,
    "category": "Any%",
    "region": null,
    "platform": "iOS",
    "emulated": false
  },
  {
    "id": "zxoqo45z",
    "game": "Where\u2019s My Head?",
    "player": "Act_",
    "player_location": "us",
    "time": 1.467,
    "category": "Any%",
    "region": "USA / NTSC",
    "platform": "iOS",
    "emulated": false
  },
  {
    "id": "mrnv2q7y",
    "game": "Where\u2019s My Head?",
    "player": "TRLittleToaster",
    "player_location": "us",
    "time": 1,
    "category": "Any%",
    "region": "USA / NTSC",
    "platform": "iOS",
    "emulated": false
  },
  {
    "id": "zq99lrry",
    "game": "Where\u2019s My Head?",
    "player": "FMG08",
    "player_location": "ie",
    "time": 155,
    "category": "Prison",
    "region": "EUR / PAL",
    "platform": "iOS",
    "emulated": false
  }
]