[
  {
    "id": "8m7o7q9y",
    "game": "Bullet Witch",
    "player": "Sasam",
    "player_location": "ca",
    "time": 4215,
    "category": "Any% NG+",
    "region": "USA / NTSC",
    "platform": "Xbox 360",
    "emulated": false
  },
  {
    "id": "mrq86k2y",
    "game": "Bullet Witch",
    "player": "Yandere_Maiden",
    "player_location": "us",
    "time": 4130,
    "category": "Any% NG+",
    "region": "USA / NTSC",
    "platform": "Xbox 360",
    "emulated": false
  },
  {
    "id": "zgkxjdny",
    "game": "Bullet Witch",
    "player": "HellVein",
    "player_location": "bg",
    "time": 2000,
    "category": "Any% NG+",
    "region": "EUR / PAL",
    "platform": "PC",
    "emulated": false
  },
  {
    "id": "m7p4qv9m",
    "game": "Bullet Witch",
    "player": "Baldram",
    "player_location": "ru",
    "time": 3309,
    "category": "Any% NG+",
    "region": "EUR / PAL",
    "platform": "PC",
    "emulated": false
  },
  {
    "id": "z53467ny",
    "game": "Bullet Witch",
    "player": "Despera",
    "player_location": "be",
    "time": 128,
    "category": "Any%",
    "region": null,
    "platform": "PC",
    "emulated": false
  },
  {
    "id": "zplo69vm",
    "game": "Bullet Witch",
    "player": "vivolus",
    "player_location": "us",
    "time": 129,
    "category": "Any%",
    "region": "USA / NTSC",
    "platform": "PC",
    "emulated": false
  },
  {
    "id": "zpdol6rz",
    "game": "Bullet Witch",
    "player": "Sameno93",
    "player_location": "jp",
    "time": 1199,
    "category": "Any% NG+",
    "region": "JPN / NTSC",
    "platform": "PC",
    "emulated": false
  },
  {
    "id": "yjpvk47y",
    "game": "Bullet Witch",
    "player": "yuyuremi",
    "player_location": "jp",
    "time": 1341,
    "category": "Any% NG+",
    "region": "JPN / NTSC",
    "platform": "PC",
    "emulated": false
  },
  {
    "id": "m36d89wm",
    "game": "Bullet Witch",
    "player": "opipieSunpaul",
    "player_location": "jp",
    "time": 1245,
    "category": "Any% NG+",
    "region": "JPN / NTSC",
    "platform": "PC",
    "emulated": false
  },
  {
    "id": "y2ee435y",
    "game": "Bullet Witch",
    "player": "kuroneko_tenhou",
    "player_location": "jp",
    "time": 1336,
    "category": "Any% NG+",
    "region": null,
    "platform": "PC",
    "emulated": false
  },
  {
    "id": "zgp70rez",
    "game": "Bullet Witch",
    "player": "zunnkoron",
    "player_location": "jp",
    "time": 4605,
    "category": "Any%",
    "region": "JPN / NTSC",
    "platform": "Xbox 360",
    "emulated": false
  },
  {
    "id": "zq703j1m",
    "game": "Bullet Witch",
    "player": "skingold",
    "player_location": "jp",
    "time": 1300,
    "category": "Any% NG+",
    "region": "JPN / NTSC",
    "platform": "PC",
    "emulated": false
  },
  {
    "id": "yv8959om",
    "game": "Bullet Witch",
    "player": "JACK4L",
    "player_location": "pl",
    "time": 1363,
    "category": "Any% NG+",
    "region": "EUR / PAL",
    "platform": "PC",
    "emulated": false
  }
]