[
  {
    "id": "6yjlp9oz",
    "game": "Buck Bumble",
    "player": "Rueake",
    "player_location": "gb/eng",
    "time": 1998.37,
    "category": "Any%",
    "region": "JPN / NTSC",
    "platform": "Nintendo 64",
    "emulated": false
  },
  {
    "id": "7ylw9lxz",
    "game": "Buck Bumble",
    "player": "Wynterise",
    "player_location": "ca",
    "time": 1819,
    "category": "Any%",
    "region": "USA / NTSC",
    "platform": "Nintendo 64",
    "emulated": true
  },
  {
    "id": "yjkj283m",
    "game": "Buck Bumble",
    "player": "AMathMonkey",
    "player_location": "ca",
    "time": 2389,
    "category": "Glitchless",
    "region": "USA / NTSC",
    "platform": "Nintendo 64",
    "emulated": false
  },
  {
    "id": "zxkr65em",
    "game": "Buck Bumble",
    "player": "UndeadBlackBird",
    "player_location": "us",
    "time": 2254,
    "category": "Glitchless",
    "region": "USA / NTSC",
    "platform": "Nintendo 64",
    "emulated": true
  },
  {
    "id": "y9n8opvz",
    "game": "Buck Bumble",
    "player": "lolaway",
    "player_location": "us",
    "time": 1958,
    "category": "Any%",
    "region": "JPN / NTSC",
    "platform": "Nintendo 64",
    "emulated": false
  },
  {
    "id": "z52oq0nz",
    "game": "Buck Bumble",
    "player": "osukarui",
    "player_location": "is",
    "time": 1894,
    "category": "Any%",
    "region": "JPN / NTSC",
    "platform": "Nintendo 64",
    "emulated": false
  },
  {
    "id": "y4q3l72m",
    "game": "Buck Bumble",
    "player": "nathanisbored",
    "player_location": "us",
    "time": 1816,
    "category": "Any%",
    "region": "USA / NTSC",
    "platform": "Nintendo 64",
    "emulated": false
  },
  {
    "id": "zpd2o58z",
    "game": "Buck Bumble",
    "player": "Bluescreen18",
    "player_location": "is",
    "time": 1978,
    "category": "Any%",
    "region": "EUR / PAL",
    "platform": "Nintendo 64",
    "emulated": false
  },
  {
    "id": "mkk8x91m",
    "game": "Buck Bumble",
    "player": "flajjin_lounge",
    "player_location": "us",
    "time": 1744,
    "category": "Any%",
    "region": "JPN / NTSC",
    "platform": "Nintendo 64",
    "emulated": false
  },
  {
    "id": "zx8evl8m",
    "game": "Buck Bumble",
    "player": "google_cheese",
    "player_location": "gb/sct",
    "time": 2414,
    "category": "Any%",
    "region": "USA / NTSC",
    "platform": "Nintendo 64",
    "emulated": true
  }
]