[
  {
    "id": "yj468n7y",
    "game": "Multiple Pok\u00e9mon Games",
    "player": "Xita",
    "player_location": "nl",
    "time": 70590,
    "category": "Catch 'em all",
    "region": "EUR / PAL",
    "platform": "Game Boy Player",
    "emulated": false
  },
  {
    "id": "z0evrq9m",
    "game": "Multiple Pok\u00e9mon Games",
    "player": "Rasschla",
    "player_location": "nl",
    "time": 300117,
    "category": "Catch 'em all",
    "region": "EUR / PAL",
    "platform": "Game Boy Player",
    "emulated": false
  },
  {
    "id": "yl4q813m",
    "game": "Multiple Pok\u00e9mon Games",
    "player": "DarkCucco",
    "player_location": "de",
    "time": 35388,
    "category": "Catch 'em all",
    "region": "EUR / PAL",
    "platform": "Game Boy Player",
    "emulated": false
  },
  {
    "id": "yo6pel7y",
    "game": "Multiple Pok\u00e9mon Games",
    "player": "Crrool",
    "player_location": "nl",
    "time": 19888,
    "category": "",
    "region": "USA / NTSC",
    "platform": "Wii",
    "emulated": false
  },
  {
    "id": "y89kx8xm",
    "game": "Multiple Pok\u00e9mon Games",
    "player": "ShadowFrost",
    "player_location": "nl",
    "time": 215125,
    "category": "Catch 'em all",
    "region": "EUR / PAL",
    "platform": "Nintendo DS",
    "emulated": false
  },
  {
    "id": "z03q034z",
    "game": "Multiple Pok\u00e9mon Games",
    "player": "SurrealGuy",
    "player_location": "de",
    "time": 25686,
    "category": "Catch 'em all",
    "region": null,
    "platform": "Game Boy Color",
    "emulated": true
  },
  {
    "id": "yo9vl10y",
    "game": "Multiple Pok\u00e9mon Games",
    "player": "Wh0misDS",
    "player_location": "us",
    "time": 55570,
    "category": "",
    "region": "EUR / PAL",
    "platform": "Wii U Virtual Console",
    "emulated": false
  },
  {
    "id": "yo280e7z",
    "game": "Multiple Pok\u00e9mon Games",
    "player": "Juanlyways",
    "player_location": "ar",
    "time": 31275,
    "category": "Main Series Glitchless",
    "region": "USA / NTSC",
    "platform": "Game Boy Player",
    "emulated": false
  },
  {
    "id": "z51ng35m",
    "game": "Multiple Pok\u00e9mon Games",
    "player": "Araya",
    "player_location": "nl",
    "time": 27060,
    "category": "Main Series Glitchless",
    "region": "EUR / PAL",
    "platform": "Game Boy Player",
    "emulated": false
  },
  {
    "id": "zg71olnz",
    "game": "Multiple Pok\u00e9mon Games",
    "player": "Quelaagging",
    "player_location": "us",
    "time": 28125,
    "category": "Main Series Glitchless",
    "region": "USA / NTSC",
    "platform": "Game Boy Player",
    "emulated": false
  },
  {
    "id": "mk2p383m",
    "game": "Multiple Pok\u00e9mon Games",
    "player": "Valyssa0",
    "player_location": "nl",
    "time": 214927,
    "category": "Catch 'em all",
    "region": "EUR / PAL",
    "platform": "Game Boy Player",
    "emulated": false
  },
  {
    "id": "znr6v58y",
    "game": "Multiple Pok\u00e9mon Games",
    "player": "Boxmeister",
    "player_location": "nl",
    "time": 71070,
    "category": "Catch 'em all",
    "region": "EUR / PAL",
    "platform": "Switch",
    "emulated": false
  },
  {
    "id": "yv3evvez",
    "game": "Multiple Pok\u00e9mon Games",
    "player": "Cryptine",
    "player_location": "ch",
    "time": 128748,
    "category": "Catch 'em all",
    "region": "EUR / PAL",
    "platform": "Switch",
    "emulated": false
  },
  {
    "id": "y823l8xy",
    "game": "Multiple Pok\u00e9mon Games",
    "player": "SmashEBrada",
    "player_location": "us",
    "time": 19016,
    "category": "",
    "region": "USA / NTSC",
    "platform": "Wii",
    "emulated": false
  },
  {
    "id": "z53rv5ey",
    "game": "Multiple Pok\u00e9mon Games",
    "player": "feranator",
    "player_location": "us",
    "time": 71210,
    "category": "Catch 'em all",
    "region": "USA / NTSC",
    "platform": "Switch",
    "emulated": false
  },
  {
    "id": "y88rqxdy",
    "game": "Multiple Pok\u00e9mon Games",
    "player": "OceanBagel",
    "player_location": "us",
    "time": 41423,
    "category": "Main Series Glitchless",
    "region": "USA / NTSC",
    "platform": "Game Boy Advance",
    "emulated": true
  },
  {
    "id": "y60nwxqy",
    "game": "Multiple Pok\u00e9mon Games",
    "player": "Zunow",
    "player_location": "jp",
    "time": 19875,
    "category": "Catch 'em all",
    "region": null,
    "platform": "Game Boy Player",
    "emulated": false
  },
  {
    "id": "ywv8d23z",
    "game": "Multiple Pok\u00e9mon Games",
    "player": "_Gon_z",
    "player_location": "jp",
    "time": 68622,
    "category": "Catch 'em all",
    "region": "JPN / NTSC",
    "platform": "Game Boy Player",
    "emulated": false
  }
]