[
  {
    "id": "zg7vv80z",
    "game": "",
    "player": "GustavoPredador",
    "player_location": "br",
    "time": 18454,
    "category": "Any%",
    "region": "USA / NTSC",
    "platform": "PlayStation 2",
    "emulated": false
  },
  {
    "id": "y65ddwqz",
    "game": "",
    "player": "Orion6347",
    "player_location": "us",
    "time": 1537,
    "category": "",
    "region": "USA / NTSC",
    "platform": "PlayStation 2",
    "emulated": false
  },
  {
    "id": "yv215v4m",
    "game": "Van Helsing",
    "player": "AiQueDeliicia",
    "player_location": "br",
    "time": 1410,
    "category": "",
    "region": "USA / NTSC",
    "platform": "PlayStation 2",
    "emulated": false
  }
]