[
  {
    "id": "zqv6jp5m",
    "game": "Vibrant Venture",
    "player": "IhaveNolifeVV",
    "player_location": "be",
    "time": 19.18,
    "category": "",
    "region": "EUR / PAL",
    "platform": "PC",
    "emulated": false
  },
  {
    "id": "y93xqxny",
    "game": "Vibrant Venture",
    "player": "Achilles",
    "player_location": null,
    "time": 20.27,
    "category": "Any%",
    "region": null,
    "platform": "PC",
    "emulated": false
  },
  {
    "id": "mrn2lndy",
    "game": "Vibrant Venture",
    "player": "N/A",
    "player_location": null,
    "time": 0.001,
    "category": "",
    "region": null,
    "platform": "PC",
    "emulated": false
  },
  {
    "id": "mkee47xm",
    "game": "Vibrant Venture",
    "player": "FrostySR",
    "player_location": null,
    "time": 342.9,
    "category": "Any%",
    "region": "EUR / PAL",
    "platform": "PC",
    "emulated": false
  },
  {
    "id": "m3x0ogdm",
    "game": "Vibrant Venture",
    "player": "Omrri",
    "player_location": "us",
    "time": 17.01,
    "category": "Any%",
    "region": "USA / NTSC",
    "platform": "PC",
    "emulated": false
  },
  {
    "id": "zpd6dqrz",
    "game": "Vibrant Venture",
    "player": "Masharmi",
    "player_location": "gb/eng",
    "time": 4.98,
    "category": "",
    "region": null,
    "platform": "PC",
    "emulated": false
  },
  {
    "id": "y8xw6e5m",
    "game": "Vibrant Venture",
    "player": "TheFluxWizard",
    "player_location": "us",
    "time": 4.36,
    "category": "Juniper%",
    "region": "USA / NTSC",
    "platform": "PC",
    "emulated": false
  },
  {
    "id": "y8xl54dm",
    "game": "Vibrant Venture",
    "player": "ToxicChimney",
    "player_location": "us",
    "time": 37.96,
    "category": "Any%",
    "region": "USA / NTSC",
    "platform": "PC",
    "emulated": false
  },
  {
    "id": "zq9n71ry",
    "game": "Vibrant Venture",
    "player": "lordgamership",
    "player_location": null,
    "time": 117.61,
    "category": "Any%",
    "region": "USA / NTSC",
    "platform": "PC",
    "emulated": false
  }
]