[
  {
    "id": "ylkx7wkz",
    "game": "In The Hunt",
    "player": "Okamikaze",
    "player_location": "gb",
    "time": 951,
    "category": "",
    "region": "JPN / NTSC",
    "platform": "Sega Saturn",
    "emulated": true
  },
  {
    "id": "z57742dm",
    "game": "In The Hunt",
    "player": "zantomun",
    "player_location": "us",
    "time": 1294,
    "category": "",
    "region": "USA / NTSC",
    "platform": "PlayStation",
    "emulated": true
  },
  {
    "id": "y2pqx29z",
    "game": "In The Hunt",
    "player": "Janet",
    "player_location": null,
    "time": 755.39,
    "category": "1 Credit",
    "region": "USA / NTSC",
    "platform": "Arcade",
    "emulated": true
  },
  {
    "id": "m7q511ez",
    "game": "In The Hunt",
    "player": "KrisTheHedgehog",
    "player_location": "fr",
    "time": 1133,
    "category": "",
    "region": "USA / NTSC",
    "platform": "Arcade",
    "emulated": true
  },
  {
    "id": "mrelr04y",
    "game": "In The Hunt",
    "player": "RitaH",
    "player_location": "br",
    "time": 1395,
    "category": "",
    "region": "USA / NTSC",
    "platform": "Arcade",
    "emulated": true
  },
  {
    "id": "mex5pe2z",
    "game": "In The Hunt",
    "player": "Asriel",
    "player_location": "br",
    "time": 758,
    "category": "Any%",
    "region": "JPN / NTSC",
    "platform": "PlayStation",
    "emulated": true
  },
  {
    "id": "y4wl69nm",
    "game": "In The Hunt",
    "player": "KumaKhan22",
    "player_location": "us",
    "time": 901,
    "category": "",
    "region": "USA / NTSC",
    "platform": "Arcade",
    "emulated": true
  },
  {
    "id": "zqggvp1m",
    "game": "In The Hunt",
    "player": "Hectorcito",
    "player_location": "ar",
    "time": 890,
    "category": "Any%",
    "region": "USA / NTSC",
    "platform": "PlayStation",
    "emulated": true
  },
  {
    "id": "me3vx20z",
    "game": "In The Hunt",
    "player": "zhutousan123",
    "player_location": "cn",
    "time": 805.33,
    "category": "1 Credit",
    "region": null,
    "platform": "Arcade",
    "emulated": true
  },
  {
    "id": "zq717jxm",
    "game": "In The Hunt",
    "player": "Sonikkustar",
    "player_location": "us",
    "time": 824,
    "category": "Any%",
    "region": null,
    "platform": "Arcade",
    "emulated": true
  }
]