[
  {
    "id": "me8ngj2m",
    "game": "",
    "player": "WASD_Shiftlock",
    "player_location": "us",
    "time": 211.082,
    "category": "1;1-10 Any% Glitch",
    "region": "USA / NTSC",
    "platform": "PC",
    "emulated": false
  },
  {
    "id": "yv13v76y",
    "game": "",
    "player": "Omitts",
    "player_location": "us",
    "time": 53.56,
    "category": "1;1-10 Any% Glitch",
    "region": "USA / NTSC",
    "platform": "PC",
    "emulated": false
  },
  {
    "id": "y4r980dz",
    "game": "",
    "player": "Necromancer333",
    "player_location": "us",
    "time": 55.065,
    "category": "1;1-10 Any% Glitch",
    "region": "USA / NTSC",
    "platform": "PC",
    "emulated": false
  },
  {
    "id": "zx635w5z",
    "game": "Mechanic Watermelon",
    "player": "NekrozOfMakoto",
    "player_location": "us",
    "time": 73.099,
    "category": "1;1-10 Any% Glitch",
    "region": "USA / NTSC",
    "platform": "PC",
    "emulated": false
  }
]