[
  {
    "id": "mk4v96xy",
    "game": "Super Double Dragon",
    "player": "HotMuffSandwich",
    "player_location": "us",
    "time": 2101,
    "category": "US/PAL 1P",
    "region": "USA / NTSC",
    "platform": "Super Nintendo",
    "emulated": false
  },
  {
    "id": "yw1rgj3z",
    "game": "Super Double Dragon",
    "player": "Kanis999",
    "player_location": "us",
    "time": 2210,
    "category": "US/PAL 2P",
    "region": "USA / NTSC",
    "platform": "Super Nintendo",
    "emulated": false
  },
  {
    "id": "oy2weo9y",
    "game": "Super Double Dragon",
    "player": "DarkMichael",
    "player_location": "de",
    "time": 2154,
    "category": "US/PAL 1P",
    "region": "USA / NTSC",
    "platform": "Super Nintendo",
    "emulated": true
  },
  {
    "id": "7ylx7kxy",
    "game": "Super Double Dragon",
    "player": "Mihairokov",
    "player_location": "ca",
    "time": 3160,
    "category": "US/PAL 1P",
    "region": "USA / NTSC",
    "platform": "Super Nintendo",
    "emulated": true
  },
  {
    "id": "9medd60y",
    "game": "Super Double Dragon",
    "player": "Kusanagi765",
    "player_location": "us",
    "time": 2286,
    "category": "JP 2P",
    "region": "JPN / NTSC",
    "platform": "Super Nintendo",
    "emulated": false
  },
  {
    "id": "z0ejp39m",
    "game": "Super Double Dragon",
    "player": "fluffytoycoy",
    "player_location": "us",
    "time": 3430,
    "category": "US/PAL 1P",
    "region": "USA / NTSC",
    "platform": "Super Nintendo",
    "emulated": true
  },
  {
    "id": "yl4jq4xm",
    "game": "Super Double Dragon",
    "player": "TheGameingChef",
    "player_location": "us",
    "time": 3265,
    "category": "US/PAL 1P",
    "region": "USA / NTSC",
    "platform": "Super Nintendo",
    "emulated": true
  },
  {
    "id": "y6nlxnjz",
    "game": "Super Double Dragon",
    "player": "Colmillito",
    "player_location": "cl",
    "time": 1663,
    "category": "US/PAL 1P",
    "region": "EUR / PAL",
    "platform": "Super Nintendo",
    "emulated": false
  },
  {
    "id": "zg79lwez",
    "game": "Super Double Dragon",
    "player": "ShinkenX",
    "player_location": "au",
    "time": 2859,
    "category": "US/PAL 1P",
    "region": "USA / NTSC",
    "platform": "Super Nintendo",
    "emulated": true
  },
  {
    "id": "y21ddv9z",
    "game": "Super Double Dragon",
    "player": "mrsancini",
    "player_location": "br",
    "time": 2372,
    "category": "JP 1P",
    "region": "JPN / NTSC",
    "platform": "Super Nintendo",
    "emulated": true
  },
  {
    "id": "z0lxgx4z",
    "game": "Super Double Dragon",
    "player": "Yamishitsuji",
    "player_location": "pe",
    "time": 1634,
    "category": "US/PAL 1P",
    "region": "EUR / PAL",
    "platform": "Super Nintendo",
    "emulated": true
  },
  {
    "id": "z53jd0gy",
    "game": "Super Double Dragon",
    "player": "TranceChaos",
    "player_location": "us",
    "time": 2342,
    "category": "US/PAL 1P",
    "region": "USA / NTSC",
    "platform": "Super Nintendo",
    "emulated": true
  },
  {
    "id": "y93k86ey",
    "game": "Super Double Dragon",
    "player": "KingRob",
    "player_location": "us",
    "time": 2042,
    "category": "JP 2P",
    "region": "JPN / NTSC",
    "platform": "Super Nintendo",
    "emulated": true
  },
  {
    "id": "zx7wqd8y",
    "game": "Super Double Dragon",
    "player": "MasterCactaur",
    "player_location": "us",
    "time": 1878,
    "category": "JP 1P",
    "region": "JPN / NTSC",
    "platform": "Super Nintendo",
    "emulated": true
  },
  {
    "id": "z123ov7y",
    "game": "Super Double Dragon",
    "player": "HurricaneMixer",
    "player_location": "us",
    "time": 2580,
    "category": "JP 1P",
    "region": "JPN / NTSC",
    "platform": "Super Nintendo",
    "emulated": false
  },
  {
    "id": "mr6p894m",
    "game": "Super Double Dragon",
    "player": "illdizzog",
    "player_location": "gb/eng",
    "time": 2061,
    "category": "JP 1P",
    "region": "JPN / NTSC",
    "platform": "Super Nintendo",
    "emulated": true
  },
  {
    "id": "zgqwep0y",
    "game": "Super Double Dragon",
    "player": "exumer",
    "player_location": "de",
    "time": 2710,
    "category": "JP 2P",
    "region": "JPN / NTSC",
    "platform": "Super Nintendo",
    "emulated": true
  },
  {
    "id": "yv0e9goz",
    "game": "Super Double Dragon",
    "player": "Cid81",
    "player_location": "pe",
    "time": 1973,
    "category": "JP 2P",
    "region": "JPN / NTSC",
    "platform": "Super Nintendo",
    "emulated": true
  },
  {
    "id": "zpdjvl8z",
    "game": "Super Double Dragon",
    "player": "joons88",
    "player_location": "fi",
    "time": 2085,
    "category": "US/PAL 1P",
    "region": "USA / NTSC",
    "platform": "Super Nintendo",
    "emulated": true
  }
]